README.md
setup.cfg
setup.py
splitty/__init__.py
splitty/splitty.py
splitty.egg-info/PKG-INFO
splitty.egg-info/SOURCES.txt
splitty.egg-info/dependency_links.txt
splitty.egg-info/not-zip-safe
splitty.egg-info/top_level.txt