Metadata-Version: 1.0
Name: splitty
Version: 0.0.8
Summary: functional approach to work with iterables in python
Home-page: https://github.com/z4r4tu5tr4/splitty
Author: Eduardo Mendes
Author-email: mendesxeduardo@gmail.com
License: MIT
Platform: UNKNOWN
